CHANGELOG.md
carrot_executor/__init__.py
carrot_executor/index.js
Camunda.py
CamundaListener.py
CamundaOpenAPI.py
carrot_executor-0.8.0.dist-info/entry_points.txt
carrot_executor-0.8.0.dist-info/WHEEL
carrot_executor-0.8.0.dist-info/METADATA
carrot_executor-0.8.0.dist-info/RECORD
