Metadata-Version: 2.1
Name: carrot-executor
Version: 0.8.0
Summary: Camunda external task Robot Framework execution scheduler
Home-page: https://github.com/datakurre/carrot-executor
License: MIT
Author: Asko Soukka
Author-email: asko.soukka@iki.fi
Requires-Python: >=3.8,<4.0
Classifier: License :: OSI Approved :: MIT License
Classifier: Programming Language :: Python :: 3
Classifier: Programming Language :: Python :: 3.8
Classifier: Programming Language :: Python :: 3.9
Requires-Dist: Pillow (>=8.3.0,<9.0.0)
Requires-Dist: pydantic (>=1.8.2,<2.0.0)
Requires-Dist: requests (>=2.25.1,<3.0.0)
Requires-Dist: robotframework (>=4.0.3,<5.0.0)
